circfirm/__init__.py
circfirm/py.typed
circfirm/startup.py
circfirm/backend/__init__.py
circfirm/backend/cache.py
circfirm/backend/device.py
circfirm/backend/github.py
circfirm/backend/s3.py
circfirm/cli/__init__.py
circfirm/cli/about.py
circfirm/cli/cache.py
circfirm/cli/config.py
circfirm/cli/current.py
circfirm/cli/detect.py
circfirm/cli/install.py
circfirm/cli/query.py
circfirm/cli/update.py
circfirm/templates/settings.yaml
circfirm/templates/settings.yaml.license
circfirm-4.0.0.dist-info/LICENSE
circfirm-4.0.0.dist-info/METADATA
circfirm-4.0.0.dist-info/NOTICE
circfirm-4.0.0.dist-info/NOTICE.license
circfirm-4.0.0.dist-info/WHEEL
circfirm-4.0.0.dist-info/entry_points.txt
circfirm-4.0.0.dist-info/top_level.txt
circfirm-4.0.0.dist-info/RECORD
