Metadata-Version: 2.2
Name: circfirm
Version: 4.0.0
Summary: CLI tool for install firmware for CircuitPython boards
Author-email: Alec Delaney <tekktrik@gmail.com>
License: MIT
Project-URL: Homepage, https://github.com/tekktrik/circfirm
Project-URL: Repository, https://github.com/tekktrik/circfirm.git
Project-URL: Issues, https://github.com/tekktrik/circfirm/issues
Keywords: adafruit,circuitpython,tool,cli,firmware,install,upload
Classifier: Intended Audience :: Developers
Classifier: Topic :: Software Development :: Embedded Systems
Classifier: Topic :: System :: Hardware
Classifier: License :: OSI Approved :: MIT License
Classifier: Development Status :: 5 - Production/Stable
Classifier: Environment :: Console
Classifier: Natural Language :: English
Classifier: Programming Language :: Python :: 3.9
Classifier: Programming Language :: Python :: 3.10
Classifier: Programming Language :: Python :: 3.11
Classifier: Programming Language :: Python :: 3.12
Classifier: Programming Language :: Python :: 3.13
Classifier: Programming Language :: Python :: Implementation :: CPython
Classifier: Operating System :: Unix
Classifier: Operating System :: Microsoft :: Windows
Classifier: Operating System :: MacOS
Classifier: Typing :: Typed
Requires-Python: >=3.9.0
License-File: LICENSE
License-File: NOTICE
License-File: NOTICE.license
Requires-Dist: boto3~=1.35
Requires-Dist: click~=8.1
Requires-Dist: click-spinner~=0.1
Requires-Dist: packaging~=24.2
Requires-Dist: psutil~=6.1
Requires-Dist: pyyaml~=6.0
Requires-Dist: requests~=2.32
Requires-Dist: boto3-stubs[essential]~=1.35
Provides-Extra: dev
Requires-Dist: build~=1.2; extra == "dev"
Requires-Dist: coverage~=7.6; extra == "dev"
Requires-Dist: pre-commit~=4.0; extra == "dev"
Requires-Dist: pytest~=8.3; extra == "dev"
Requires-Dist: sphinx~=7.4; extra == "dev"
Requires-Dist: sphinx-tabs~=3.4; extra == "dev"
Requires-Dist: sphinx-rtd-theme~=3.0; extra == "dev"
